adsi/__init__.py
authorization/__init__.py
axcontrol/__init__.py
axdebug/__init__.py
axscript/__init__.py
bits/__init__.py
directsound/__init__.py
exchange/__init__.py
ifilter/__init__.py
internet/__init__.py
mapi/__init__.py
mmapfile/__init__.py
netbios/__init__.py
ntsecuritycon/__init__.py
odbc/__init__.py
perfmon/__init__.py
propsys/__init__.py
pythoncom/__init__.py
pywin32_testutil/__init__.py
pywintypes/__init__.py
servicemanager/__init__.py
shell/__init__.py
taskscheduler/__init__.py
timer/__init__.py
win2kras/__init__.py
win32api/__init__.py
win32auth/__init__.py
win32clipboard/__init__.py
win32com/__init__.py
win32com/storagecon.py
win32com/universal.py
win32com/authorization/__init__.py
win32com/authorization/authorization.py
win32com/axscript/__init__.py
win32com/axscript/client.py
win32com/client/__init__.py
win32com/client/dynamic.py
win32com/client/gencache.py
win32com/client/makepy.py
win32com/client/selecttlb.py
win32com/server/__init__.py
win32com/server/exception.py
win32com/server/policy.py
win32com/server/util.py
win32com/servers/__init__.py
win32com/servers/dictionary.py
win32com/servers/interp.py
win32com/shell/__init__.py
win32com/shell/shell.py
win32com/shell/shellcon.py
win32com/test/__init__.py
win32com/test/util.py
win32compat-221.26.dist-info/DESCRIPTION.rst
win32compat-221.26.dist-info/METADATA
win32compat-221.26.dist-info/RECORD
win32compat-221.26.dist-info/WHEEL
win32compat-221.26.dist-info/metadata.json
win32compat-221.26.dist-info/top_level.txt
win32con/__init__.py
win32console/__init__.py
win32cred/__init__.py
win32crypt/__init__.py
win32event/__init__.py
win32evtlog/__init__.py
win32file/__init__.py
win32gui_struct/__init__.py
win32help/__init__.py
win32inet/__init__.py
win32inetcon/__init__.py
win32internet/__init__.py
win32job/__init__.py
win32kras/__init__.py
win32lz/__init__.py
win32net/__init__.py
win32pdh/__init__.py
win32pipe/__init__.py
win32print/__init__.py
win32process/__init__.py
win32profile/__init__.py
win32propsys/__init__.py
win32ras/__init__.py
win32rcparser/__init__.py
win32scheduler/__init__.py
win32security/__init__.py
win32service/__init__.py
win32shell/__init__.py
