Metadata-Version: 1.0
Name: win32compat
Version: 221.26
Summary: Python for Window Extensions
Home-page: http://sourceforge.net/projects/pywin32/
Author: Mark Hammond (et al)
Author-email: mhammond@users.sourceforge.net
License: GNU GPL v3
Platform: UNKNOWN
